[{"Date":"Tuesday 17 May 2016 ","Jackpot":"16,000,000"},{"Date":"Friday 27 May 2016 ","Jackpot":"36,000,000"},{"Date":"Tuesday 31 May 2016 ","Jackpot":"41,000,000"},{"Date":"Tuesday 14 June 2016","Jackpot":"15,000,000"},{"Date":"Friday 17 June 2016","Jackpot":"24,000,000"},{"Date":"Tuesday 5 July 2016","Jackpot":"15,000,000"},{"Date":"Friday 8 July 2016","Jackpot":"23,000,000"},{"Date":"Friday 8 July 2016","Jackpot":"23,000,000"},{"Date":"Friday 8 July 2016","Jackpot":"23,000,000"},{"Date":"Friday 8 July 2016","Jackpot":"23,000,000"},{"Date":"Friday 8 July 2016","Jackpot":"23,000,000"},{"Date":"Friday 8 July 2016","Jackpot":"23,000,000"},{"Date":"Friday 8 July 2016","Jackpot":"23,000,000"},{"Date":"Friday 8 July 2016","Jackpot":"23,000,000"},{"Date":"Friday 8 July 2016","Jackpot":"23,000,000"},{"Date":"Friday 8 July 2016","Jackpot":"23,000,000"},{"Date":"Friday 8 July 2016","Jackpot":"23,000,000"},{"Date":"Friday 8 July 2016","Jackpot":"23,000,000"},{"Date":"Friday 8 July 2016","Jackpot":"23,000,000"},{"Date":"Friday 8 July 2016","Jackpot":"23,000,000"},{"Date":"Friday 8 July 2016","Jackpot":"23,000,000"},{"Date":"Friday 8 July 2016","Jackpot":"23,000,000"}]